{"commitInfo":{"timestamp":1773824327834,"operation":"WRITE","operationParameters":{"mode":"Overwrite","partitionBy":"[]"},"readVersion":4,"isolationLevel":"Serializable","isBlindAppend":false,"operationMetrics":{"numFiles":"3","numRemovedFiles":"12","numRemovedBytes":"6489","numOutputRows":"50","numOutputBytes":"1675"},"engineInfo":"Apache-Spark/4.1.1 Delta-Lake/4.1.0","txnId":"500bb309-a044-43ba-8574-568a40d4f4f1"}}
{"add":{"path":"part-00000-f0b63910-2018-4dac-930b-4e5f2f7efae7-c000.snappy.parquet","partitionValues":{},"size":561,"modificationTime":1773824327396,"dataChange":true,"stats":"{\"numRecords\":17,\"minValues\":{\"id\":16},\"maxValues\":{\"id\":32},\"nullCount\":{\"id\":0}}"}}
{"add":{"path":"part-00001-c93b3d35-c695-4499-9313-f53081b8970d-c000.snappy.parquet","partitionValues":{},"size":558,"modificationTime":1773824327382,"dataChange":true,"stats":"{\"numRecords\":17,\"minValues\":{\"id\":33},\"maxValues\":{\"id\":49},\"nullCount\":{\"id\":0}}"}}
{"add":{"path":"part-00002-3c6ef4f0-c5dd-46ea-ad30-e76feca8cbc0-c000.snappy.parquet","partitionValues":{},"size":556,"modificationTime":1773824327382,"dataChange":true,"stats":"{\"numRecords\":16,\"minValues\":{\"id\":0},\"maxValues\":{\"id\":15},\"nullCount\":{\"id\":0}}"}}
{"remove":{"path":"part-00001-c66d22fd-c61b-40b3-94b5-007b30c99f93-c000.snappy.parquet","deletionTimestamp":1773824327831,"dataChange":true,"extendedFileMetadata":true,"partitionValues":{},"size":521}}
{"remove":{"path":"part-00000-6d18ed9b-57c6-4470-8599-eb97473e4fb4-c000.snappy.parquet","deletionTimestamp":1773824327831,"dataChange":true,"extendedFileMetadata":true,"partitionValues":{},"size":522}}
{"remove":{"path":"part-00000-b183a987-7094-47f6-a058-34f1c2414e5f-c000.snappy.parquet","deletionTimestamp":1773824327831,"dataChange":true,"extendedFileMetadata":true,"partitionValues":{},"size":556}}
{"remove":{"path":"part-00002-8ab6bf29-52c6-4a4f-8723-c664aaeba2d7-c000.snappy.parquet","deletionTimestamp":1773824327831,"dataChange":true,"extendedFileMetadata":true,"partitionValues":{},"size":558}}
{"remove":{"path":"part-00004-ce5a339a-cf74-427e-88f3-ac9d275f0891-c000.snappy.parquet","deletionTimestamp":1773824327831,"dataChange":true,"extendedFileMetadata":true,"partitionValues":{},"size":521}}
{"remove":{"path":"part-00005-829767b9-f4e7-42da-8f47-be638907b51a-c000.snappy.parquet","deletionTimestamp":1773824327831,"dataChange":true,"extendedFileMetadata":true,"partitionValues":{},"size":561}}
{"remove":{"path":"part-00003-9dea2e5f-e917-4780-ba9a-afb6128a2c41-c000.snappy.parquet","deletionTimestamp":1773824327831,"dataChange":true,"extendedFileMetadata":true,"partitionValues":{},"size":557}}
{"remove":{"path":"part-00005-6d9e5ea1-7be1-44cc-8f03-fbd6aea2fcb1-c000.snappy.parquet","deletionTimestamp":1773824327831,"dataChange":true,"extendedFileMetadata":true,"partitionValues":{},"size":527}}
{"remove":{"path":"part-00003-3a71d529-8be2-49ca-a598-f473c0311ca1-c000.snappy.parquet","deletionTimestamp":1773824327831,"dataChange":true,"extendedFileMetadata":true,"partitionValues":{},"size":521}}
{"remove":{"path":"part-00001-9b70ca9e-3090-4bd3-a335-859bff498feb-c000.snappy.parquet","deletionTimestamp":1773824327831,"dataChange":true,"extendedFileMetadata":true,"partitionValues":{},"size":561}}
{"remove":{"path":"part-00004-29cd7abb-ff76-4a89-96fb-7fbfea62c2bb-c000.snappy.parquet","deletionTimestamp":1773824327831,"dataChange":true,"extendedFileMetadata":true,"partitionValues":{},"size":559}}
{"remove":{"path":"part-00002-2c443484-44f4-4ba0-9fe0-24865df1ef0c-c000.snappy.parquet","deletionTimestamp":1773824327831,"dataChange":true,"extendedFileMetadata":true,"partitionValues":{},"size":525}}
